.gitignore
.pre-commit-config.yaml
.pylintrc
.readthedocs.yml
CODE_OF_CONDUCT.md
LICENSE
README.rst
README.rst.license
pyproject.toml
requirements.txt
setup.py
.github/workflows/build.yml
.github/workflows/release.yml
LICENSES/CC-BY-4.0.txt
LICENSES/MIT.txt
LICENSES/Unlicense.txt
circuitpython_wiichuck.egg-info/PKG-INFO
circuitpython_wiichuck.egg-info/SOURCES.txt
circuitpython_wiichuck.egg-info/dependency_links.txt
circuitpython_wiichuck.egg-info/requires.txt
circuitpython_wiichuck.egg-info/top_level.txt
docs/api.rst
docs/api.rst.license
docs/conf.py
docs/examples.rst
docs/examples.rst.license
docs/index.rst
docs/index.rst.license
docs/_static/favicon.ico
docs/_static/favicon.ico.license
examples/classic_controller_pro_simpletest.py
examples/classic_controller_simpletest.py
examples/dj_table_simpletest.py
examples/guitar_simpletest.py
examples/nunchuk_accel_mouse.py
examples/nunchuk_analog_mouse.py
examples/snes_controller_simpletest
examples/udraw_mouse.py
examples/udraw_simpletest.py
examples/wiichuck_simpletest.py
wiichuck/__init__.py
wiichuck/classic_controller.py
wiichuck/dj_table.py
wiichuck/guitar.py
wiichuck/nunchuk.py
wiichuck/udraw.py