Metadata-Version: 2.1
Name: circuitpython-wiichuck
Version: 0.0.1
Summary: CircuitPython driver for Nintento WiiMote I2C Accessory Devices
Home-page: https://github.com/jfurcean/CircuitPython_WiiChuck
Author: John Furcean
Author-email: john@furcean.com
License: MIT
Keywords: adafruit blinka circuitpython micropython wiichuck Wii Nunchuck ClassicController WiiMote Guitar DJ uDraw
Platform: UNKNOWN
Classifier: Development Status :: 3 - Alpha
Classifier: Intended Audience :: Developers
Classifier: Topic :: Software Development :: Libraries
Classifier: Topic :: System :: Hardware
Classifier: License :: OSI Approved :: MIT License
Classifier: Programming Language :: Python :: 3
Classifier: Programming Language :: Python :: 3.4
Classifier: Programming Language :: Python :: 3.5
